presentation_card/__init__.py
presentation_card/frontend/index.html
presentation_card/frontend/css/style.css
presentation_card/frontend/images/profile.png
presentation_card/frontend/js/main.js
presentation_card/frontend/js/script.js
presentation_card/frontend/js/streamlit-component-lib.js
presentation_card-0.1.8.dist-info/LICENSE
presentation_card-0.1.8.dist-info/METADATA
presentation_card-0.1.8.dist-info/WHEEL
presentation_card-0.1.8.dist-info/top_level.txt
presentation_card-0.1.8.dist-info/RECORD
